dict2anki/__init__.py
dict2anki/__main__.py
dict2anki/cli.py
dict2anki/htmls.py
dict2anki/net.py
dict2anki/utils.py
dict2anki/extractors/__init__.py
dict2anki/extractors/cambridge.py
dict2anki/extractors/extractor.py
dict2anki-0.6.1.dist-info/LICENSE
dict2anki-0.6.1.dist-info/METADATA
dict2anki-0.6.1.dist-info/WHEEL
dict2anki-0.6.1.dist-info/entry_points.txt
dict2anki-0.6.1.dist-info/top_level.txt
dict2anki-0.6.1.dist-info/RECORD
