Metadata-Version: 2.1
Name: dict2anki
Version: 0.6.1
Summary: dict2anki is a tool converting words to Anki cards.
Home-page: https://github.com/qianbinbin/dict2anki
Author: Binbin Qian
Author-email: qianbinbin@hotmail.com
License: UNKNOWN
Platform: UNKNOWN
Requires-Python: >=3.7
